[
  {
    "title": "Ads 1",
    "startDate": 1,
    "endDate": 6
  },
  {
    "title": "Ads 2",
    "startDate": 22,
    "endDate": 25
  },
  {
    "title": "Ads 3",
    "startDate": 5,
    "endDate": 16
  },
  {
    "title": "Ads 4",
    "startDate": 11,
    "endDate": 22
  },
  {
    "title": "Ads 5",
    "startDate": 16,
    "endDate": 25
  },
  {
    "title": "Ads 6",
    "startDate": 12,
    "endDate": 22
  },
  {
    "title": "Ads 7",
    "startDate": 24,
    "endDate": 27
  },
  {
    "title": "Ads 8",
    "startDate": 1,
    "endDate": 30
  },
  {
    "title": "Ads 9",
    "startDate": 26,
    "endDate": 27
  },
  {
    "title": "Ads 10",
    "startDate": 10,
    "endDate": 12
  },
  {
    "title": "Ads 11",
    "startDate": 26,
    "endDate": 28
  },
  {
    "title": "Ads 12",
    "startDate": 4,
    "endDate": 6
  },
  {
    "title": "Ads 13",
    "startDate": 5,
    "endDate": 6
  },
  {
    "title": "Ads 14",
    "startDate": 7,
    "endDate": 11
  },
  {
    "title": "Ads 15",
    "startDate": 20,
    "endDate": 21
  }
]
